<lock>
 <warden>Nargarawr</warden>
 <cellmates>
  <cellmate>Nargarawr</cellmate>
 </cellmates>
 <region>
  <name>Pink</name>
   <entrance>
    <x>26.0</x>
    <y>78.0</y>
    <z>256.0</z>
   </entrance>
  <min_point>
   <world>CraftWorld{name=world}</world>
   <x>25.0</x>
   <y>77.0</y>
   <z>248.0</z>
  </min_point>
  <max_point>
   <world>CraftWorld{name=world}</world>
   <x>28.0</x>
   <y>80.0</y>
   <z>253.0</z>
  </max_point>
 </region>
</lock>
<lock>
 <warden>N/A</warden>
 <cellmates>
 </cellmates>
 <region>
  <name>Blue</name>
   <entrance>
    <x>26.0</x>
    <y>78.0</y>
    <z>256.0</z>
   </entrance>
  <min_point>
   <world>CraftWorld{name=world}</world>
   <x>23.0</x>
   <y>79.0</y>
   <z>257.0</z>
  </min_point>
  <max_point>
   <world>CraftWorld{name=world}</world>
   <x>23.0</x>
   <y>79.0</y>
   <z>257.0</z>
  </max_point>
 </region>
</lock>
<lock>
 <warden>N/A</warden>
 <cellmates>
 </cellmates>
 <region>
  <name>Green</name>
   <no_entrance/>
  <min_point>
   <world>CraftWorld{name=world}</world>
   <x>17.0</x>
   <y>77.0</y>
   <z>245.0</z>
  </min_point>
  <max_point>
   <world>CraftWorld{name=world}</world>
   <x>17.0</x>
   <y>77.0</y>
   <z>245.0</z>
  </max_point>
 </region>
</lock>
